<idea-plugin>

  <extensionPoints>
    <extensionPoint name="server" beanClass="com.redhat.devtools.intellij.lsp4ij.ServerExtensionPointBean">
      <with attribute="clientClass" implements="com.redhat.devtools.intellij.lsp4ij.LanguageClientImpl"/>
      <with attribute="serverClass" implements="org.eclipse.lsp4j.services.LanguageServer"/>
    </extensionPoint>
    <extensionPoint name="languageMapping" beanClass="com.redhat.devtools.intellij.lsp4ij.LanguageMappingExtensionPointBean"/>
    <extensionPoint name="serverIconProvider" beanClass="com.redhat.devtools.intellij.lsp4ij.ServerIconProviderExtensionPointBean"/>
  </extensionPoints>

  <extensions defaultExtensionNs="com.intellij">
    <applicationConfigurable groupId="language"
                           id="LanguageServers"
                           provider="com.redhat.devtools.intellij.lsp4ij.settings.LanguageServerListConfigurableProvider"/>
    <applicationService id="com.redhat.devtools.intellij.lsp4ij.settings.UserDefinedLanguageServerSettings"
                        serviceImplementation="com.redhat.devtools.intellij.lsp4ij.settings.UserDefinedLanguageServerSettings"/>
    <toolWindow id="Language Servers"
                anchor="bottom"
                factoryClass="com.redhat.devtools.intellij.lsp4ij.console.LSPConsoleToolWindowFactory"
                canCloseContents="false" />
  </extensions>

  <actions resource-bundle="messages.LanguageServerBundle">
    <action id="com.redhat.devtools.intellij.lsp4ij.console.explorer.actions.RestartServerAction"
          class="com.redhat.devtools.intellij.lsp4ij.console.explorer.actions.RestartServerAction"
          icon="AllIcons.Actions.Restart" />
    <action id="com.redhat.devtools.intellij.lsp4ij.console.explorer.actions.StopServerAction"
            class="com.redhat.devtools.intellij.lsp4ij.console.explorer.actions.StopServerAction"
            icon="AllIcons.Actions.Suspend" />
  </actions>

  <extensions defaultExtensionNs="com.intellij">
    <applicationService serviceImplementation="com.redhat.devtools.intellij.lsp4ij.lifecycle.LanguageServerLifecycleManager"/>
    <projectService serviceImplementation="com.redhat.devtools.intellij.lsp4ij.LanguageServiceAccessor"/>
    <projectService serviceImplementation="com.redhat.devtools.intellij.lsp4ij.lifecycle.LanguageServerLifecycleManager"/>
    <completion.contributor id="LSPCompletionContributor" language="any" implementationClass="com.redhat.devtools.intellij.lsp4ij.operations.completion.LSContentAssistProcessor" order="first"/>
    <inspectionToolProvider implementation="com.redhat.devtools.intellij.lsp4ij.operations.diagnostics.LSPInspectionToolProvider"/>
    <gotoDeclarationHandler implementation="com.redhat.devtools.intellij.lsp4ij.operations.navigation.LSPGotoDeclarationHandler"/>
    <highlightUsagesHandlerFactory implementation="com.redhat.devtools.intellij.lsp4ij.operations.highlight.LSPHighlightUsagesHandlerFactory"/>
  </extensions>

  <applicationListeners>
    <listener topic="com.intellij.openapi.project.ProjectManagerListener"
              class="com.redhat.devtools.intellij.lsp4ij.ConnectDocumentToLanguageServerSetupParticipant" />
  </applicationListeners>

</idea-plugin>
